ethpm_cli/__init__.py
ethpm_cli/config.py
ethpm_cli/constants.py
ethpm_cli/exceptions.py
ethpm_cli/main.py
ethpm_cli/parser.py
ethpm_cli/validation.py
ethpm_cli/_utils/__init__.py
ethpm_cli/_utils/etherscan.py
ethpm_cli/_utils/filesystem.py
ethpm_cli/_utils/ipfs.py
ethpm_cli/_utils/logger.py
ethpm_cli/_utils/shellart.py
ethpm_cli/_utils/solc.py
ethpm_cli/_utils/various.py
ethpm_cli/_utils/xdg.py
ethpm_cli/assets/v3.json
ethpm_cli/commands/__init__.py
ethpm_cli/commands/activate.py
ethpm_cli/commands/auth.py
ethpm_cli/commands/etherscan.py
ethpm_cli/commands/get.py
ethpm_cli/commands/install.py
ethpm_cli/commands/manifest.py
ethpm_cli/commands/package.py
ethpm_cli/commands/registry.py
ethpm_cli/commands/release.py
ethpm_cli/commands/scraper.py
ethpm_cli-0.3.0.dist-info/LICENSE
ethpm_cli-0.3.0.dist-info/METADATA
ethpm_cli-0.3.0.dist-info/WHEEL
ethpm_cli-0.3.0.dist-info/entry_points.txt
ethpm_cli-0.3.0.dist-info/top_level.txt
ethpm_cli-0.3.0.dist-info/RECORD
