Metadata-Version: 2.1
Name: ethpm-cli
Version: 0.3.0
Summary: ethpm-cli: CLI for EthPM
Home-page: https://github.com/ethereum/ethpm-cli
Author: The Ethereum Foundation
Author-email: snakecharmers@ethereum.org
License: MIT
Keywords: ethereum
Platform: UNKNOWN
Classifier: Development Status :: 3 - Alpha
Classifier: Intended Audience :: Developers
Classifier: License :: OSI Approved :: MIT License
Classifier: Natural Language :: English
Classifier: Programming Language :: Python :: 3
Classifier: Programming Language :: Python :: 3.7
Requires-Python: >=3.7, <4
Requires-Dist: eth-hash[pysha3] (<1,>=0.2.0)
Requires-Dist: ipython (<8,>=7.11.1)
Requires-Dist: requests (<3,>=2.22.0)
Requires-Dist: termcolor (<2.0.0,>=1.1.0)
Requires-Dist: web3[tester] (<6,>=5.13.0)
Provides-Extra: dev
Requires-Dist: bumpversion (<1,>=0.5.3) ; extra == 'dev'
Requires-Dist: pytest-watch (<5,>=4.1.0) ; extra == 'dev'
Requires-Dist: wheel ; extra == 'dev'
Requires-Dist: twine ; extra == 'dev'
Requires-Dist: pexpect (<5,>=4.7.0) ; extra == 'dev'
Requires-Dist: pytest (<5,>=4.4.0) ; extra == 'dev'
Requires-Dist: pytest-xdist (<2,>=1.29) ; extra == 'dev'
Requires-Dist: tox (<3,>=2.9.1) ; extra == 'dev'
Requires-Dist: black (<20,>=19.3b0) ; extra == 'dev'
Requires-Dist: flake8 (<4,>=3.7.0) ; extra == 'dev'
Requires-Dist: isort (<5,>=4.3.17) ; extra == 'dev'
Requires-Dist: mypy (<0.800,>=0.770) ; extra == 'dev'
Requires-Dist: pydocstyle (<4,>=3.0.0) ; extra == 'dev'
Requires-Dist: Sphinx (<2,>=1.6.5) ; extra == 'dev'
Requires-Dist: sphinx-rtd-theme (>=0.1.9) ; extra == 'dev'
Requires-Dist: sphinx-argparse (<1,>=0.2.5) ; extra == 'dev'
Provides-Extra: doc
Requires-Dist: Sphinx (<2,>=1.6.5) ; extra == 'doc'
Requires-Dist: sphinx-rtd-theme (>=0.1.9) ; extra == 'doc'
Requires-Dist: sphinx-argparse (<1,>=0.2.5) ; extra == 'doc'
Provides-Extra: lint
Requires-Dist: black (<20,>=19.3b0) ; extra == 'lint'
Requires-Dist: flake8 (<4,>=3.7.0) ; extra == 'lint'
Requires-Dist: isort (<5,>=4.3.17) ; extra == 'lint'
Requires-Dist: mypy (<0.800,>=0.770) ; extra == 'lint'
Requires-Dist: pydocstyle (<4,>=3.0.0) ; extra == 'lint'
Provides-Extra: test
Requires-Dist: pexpect (<5,>=4.7.0) ; extra == 'test'
Requires-Dist: pytest (<5,>=4.4.0) ; extra == 'test'
Requires-Dist: pytest-xdist (<2,>=1.29) ; extra == 'test'
Requires-Dist: tox (<3,>=2.9.1) ; extra == 'test'
